sshcmds/__init__.py
sshcmds/runcmds.py
sshcmds/sshcli.py
sshcmds-0.1.6.dist-info/METADATA
sshcmds-0.1.6.dist-info/WHEEL
sshcmds-0.1.6.dist-info/entry_points.txt
sshcmds-0.1.6.dist-info/top_level.txt
sshcmds-0.1.6.dist-info/RECORD
