Metadata-Version: 2.1
Name: sshcmds
Version: 0.1.6
Summary: A package to run ssh commands
Home-page: https://github.com/colmagi
Author: James You
Author-email: jamesyou314@gmail.com
License: UNKNOWN
Platform: UNKNOWN
Classifier: Programming Language :: Python :: 3
Classifier: License :: OSI Approved :: MIT License
Classifier: Operating System :: OS Independent
Requires-Python: >=3.9.1
